gptparse/__init__.py
gptparse/cli.py
gptparse/config/__init__.py
gptparse/config/logging_config.py
gptparse/handlers/__init__.py
gptparse/handlers/base.py
gptparse/handlers/docling_handler.py
gptparse/handlers/image_handler.py
gptparse/handlers/pdf_handler.py
gptparse/models/__init__.py
gptparse/models/base.py
gptparse/models/model_interface.py
gptparse/models/providers/anthropic_provider.py
gptparse/models/providers/google_provider.py
gptparse/models/providers/openai_provider.py
gptparse/models/types.py
gptparse/modes/__init__.py
gptparse/modes/fast.py
gptparse/modes/hybrid.py
gptparse/modes/vision.py
gptparse/outputs.py
gptparse/utils/__init__.py
gptparse/utils/callbacks.py
gptparse/utils/image_utils.py
gptparse/utils/pdf_utils.py
gptparse-0.3.0.dist-info/LICENSE
gptparse-0.3.0.dist-info/METADATA
gptparse-0.3.0.dist-info/WHEEL
gptparse-0.3.0.dist-info/entry_points.txt
gptparse-0.3.0.dist-info/RECORD
