Metadata-Version: 2.1
Name: gptparse
Version: 0.3.0
Summary: A tool for converting PDF documents to Markdown using OCR and vision language models
Author: Sanjay Nadhavajhala
Author-email: sanjay@acorn.io
Requires-Python: >=3.10,<4.0
Classifier: License :: OSI Approved :: Apache Software License
Classifier: Operating System :: OS Independent
Classifier: Programming Language :: Python :: 3
Classifier: Programming Language :: Python :: 3.10
Classifier: Programming Language :: Python :: 3.11
Classifier: Programming Language :: Python :: 3.12
Classifier: Programming Language :: Python :: 3.13
Requires-Dist: Pillow (==10.4.0)
Requires-Dist: PyPDF2 (==3.0.1)
Requires-Dist: PyYAML (==6.0.2)
Requires-Dist: beautifulsoup4 (==4.12.3)
Requires-Dist: certifi (==2024.8.30)
Requires-Dist: cffi (==1.17.1)
Requires-Dist: charset-normalizer (==3.4.0)
Requires-Dist: click (==8.1.7)
Requires-Dist: decorator (==5.1.1)
Requires-Dist: docling (>=2.4.2,<3.0.0)
Requires-Dist: filelock (==3.16.1)
Requires-Dist: fsspec (==2024.9.0)
Requires-Dist: google-ai-generativelanguage (==0.6.10)
Requires-Dist: google-api-core (==2.21.0)
Requires-Dist: google-auth (==2.35.0)
Requires-Dist: google-generativeai (==0.8.3)
Requires-Dist: grpcio (==1.66.2)
Requires-Dist: grpcio-status (==1.66.2)
Requires-Dist: httpcore (==1.0.6)
Requires-Dist: httpx (==0.27.2)
Requires-Dist: huggingface-hub (==0.25.2)
Requires-Dist: idna (==3.10)
Requires-Dist: langchain-anthropic (==0.2.3)
Requires-Dist: langchain-google-genai (==2.0.1)
Requires-Dist: langchain-openai (>=0.2.6,<0.3.0)
Requires-Dist: markdown-it-py (==3.0.0)
Requires-Dist: mistune (==3.0.2)
Requires-Dist: pdf2image (==1.17.0)
Requires-Dist: platformdirs (==4.3.6)
Requires-Dist: psutil (==6.0.0)
Requires-Dist: pycryptodome (>=3.21.0,<4.0.0)
Requires-Dist: pymupdf4llm (>=0.0.17,<0.0.18)
Requires-Dist: requests (==2.32.3)
Requires-Dist: six (==1.16.0)
Requires-Dist: tqdm (==4.66.5)
Requires-Dist: traitlets (==5.14.3)
Project-URL: Homepage, https://github.com/gptscript-ai/gptparse
Project-URL: Repository, https://github.com/gptscript-ai/gptparse
